{
  "version": "1.5.1",
  "releaseDate": "2026-06-26",
  "notes": "ADAptify panel isolation fix: the widget is now appended to <html> (a sibling of <body>) and every visitor effect is scoped to <body>, so the panel itself can never be recolored, filtered, zoomed, or resized by the page — verified the menu stays readable under High Contrast/Invert. ADAptify full option set: the widget now offers Readable Font, Highlight Titles/Links, Text Magnifier, Content Scaling + Font Size + Line Height + Letter Spacing steppers (±10% per click), text alignment, Dark/Light/High contrast, Monochrome, Invert, High/Low saturation, custom text/title/background colors, Mute Sounds, Hide Images, Reading Guide, Reading Mask, Stop Animations, Highlight on Hover/Click, and Large Cursor — grouped into Content/Color/Navigation sections, all persisted per visitor. Updates are now ALWAYS automatic: the manual update card is removed and every site installs the latest engine at login, so no one can run a stale build (re-introduce a gate before a major release if needed). Security: enforce HTTPS for credentials. A new root .htaccess redirects all HTTP traffic to HTTPS site-wide (proxy-aware to avoid redirect loops), and api.php now refuses sign-in / password / secret actions over plain HTTP as a server-side backstop (localhost exempt; toggle with 'require_https' in config.secret.php). Passwords were already hashed at rest with Argon2id/bcrypt; this closes the in-transit gap. Hotfix (1.4.1): neutralized a literal closing-script sequence in an ADAptify comment that truncated admin/index.html and broke login. ADAptify — a site-wide accessibility widget (contrast, text size, grayscale, invert, readable font, highlight links, big cursor, pause motion) with its own CMS tab. Enable/disable, placement, and brand colors are stored server-side in data/adaptify.json and apply to every page instantly. One-click install drops the widget script across all pages. Plus the 1.3.0 work: server-level page list, automatic server connection, server-side settings, Revisions ledger, faithful HTML import, WAF-proof multipart save, square media picker + 16:9 desktop editor, FAQ/accordion editing, and Privacy Policy generator.",
  "files": [
    "admin/index.html",
    "admin/db.php",
    "block-renderer.jsx",
    "blog-post.jsx",
    "interior-shell.jsx",
    "posts.jsx",
    "preview.html",
    "adaptify.js"
  ],
  "apiManual": true,
  "apiNote": "admin/api.php holds this site's secrets (API token) and is never auto-updated. If a release changes api.php, update it by hand. 1.4.2 adds HTTPS enforcement to api.php (the credential-action backstop) — deploy the updated api.php and the new root .htaccess by hand to get the full effect; the redirect and guard only protect a site once those two files are in place. 1.4.0 adds 'adaptify.js' to api.php's repo-fetch allow-list — only needed for installing the widget from a PRIVATE repo."
}
